automaton_engine/__init__.py
automaton_engine/__main__.py
automaton_engine/engine.py
automaton_engine/runner.py
automaton_engine/actions/__init__.py
automaton_engine/actions/awx.py
automaton_engine/actions/notify.py
automaton_engine-1.0.2.dist-info/LICENSE
automaton_engine-1.0.2.dist-info/METADATA
automaton_engine-1.0.2.dist-info/WHEEL
automaton_engine-1.0.2.dist-info/entry_points.txt
automaton_engine-1.0.2.dist-info/top_level.txt
automaton_engine-1.0.2.dist-info/RECORD
