Metadata-Version: 2.1
Name: automaton-engine
Version: 1.0.2
Summary: Simple, Event-driven Automation in Python using Elasticsearch data to inform automation decisions
Home-page: https://github.com/jgericke/automaton_engine
Author: Julian Gericke, LSD Information Technology
Author-email: julian@lsd.co.za
License: MIT
Platform: UNKNOWN
Classifier: Development Status :: 5 - Production/Stable
Classifier: Environment :: Console
Classifier: Environment :: MacOS X
Classifier: Operating System :: MacOS :: MacOS X
Classifier: Operating System :: POSIX :: Linux
Classifier: Programming Language :: Python :: 3
Classifier: Programming Language :: Python :: 3.7
Classifier: Topic :: System :: Systems Administration
Classifier: Topic :: System :: Monitoring
Classifier: Topic :: System :: Logging
Requires-Python: ~=3.7
Requires-Dist: asyncio (>=3.4.3)
Requires-Dist: aiohttp (>=3.5.4)
Requires-Dist: biome (>=0.1.3)
Provides-Extra: dev
Requires-Dist: coverage (>=4.5.3) ; extra == 'dev'
Requires-Dist: black (>=19.3b0) ; extra == 'dev'
Requires-Dist: setuptools-black (>=0.1.4) ; extra == 'dev'
Requires-Dist: flake8 (>=3.7.7) ; extra == 'dev'
Requires-Dist: pre-commit (>=1.16.1) ; extra == 'dev'
